pygcc/.DS_Store
pygcc/PeriodicTableJSON.json
pygcc/__init__.py
pygcc/clay_elements.dat
pygcc/clay_thermocalc.py
pygcc/default_db/PHREEQC_ThermoddemV1.10_15Dec2020.dat
pygcc/default_db/berman.dat
pygcc/default_db/data0.dat
pygcc/default_db/phreeqc.dat
pygcc/default_db/pitzer.dat
pygcc/default_db/speq21.dat
pygcc/default_db/speq21_dimer.dat
pygcc/default_db/speq23.dat
pygcc/default_db/speq23_dimer.dat
pygcc/default_db/supcrtbl.dat
pygcc/default_db/thermo.2021.dat
pygcc/default_db/thermo.com.dat
pygcc/default_db/thermo.com.tdat
pygcc/default_db/thermo_cemdata_mar.tdat
pygcc/default_db/thermo_latest.tdat
pygcc/ion_size.txt
pygcc/pygcc_utils.py
pygcc/read_db.py
pygcc/solid_solution.py
pygcc/species_eos.py
pygcc/version_issue/clay_thermocalc copy.py
pygcc/version_issue/pygcc_utils copy.py
pygcc/version_issue/read_db copy.py
pygcc/version_issue/species_eos copy.py
pygcc/version_issue/water_eos copy.py
pygcc/water_eos.py
pygcc-1.5.1.dist-info/METADATA
pygcc-1.5.1.dist-info/WHEEL
pygcc-1.5.1.dist-info/licenses/LICENSE
pygcc-1.5.1.dist-info/RECORD
