Metadata-Version: 2.4
Name: pygcc
Version: 1.5.1
Summary: A tool for thermodynamic calculations and geochemical database generation
License-Expression: GPL-3.0-or-later
License-File: LICENSE
Keywords: Geochemistry,Thermodynamic database,Thermodynamic calculations,Solid-solutions,Variable clay minerals,PHREEQC,GWB,EQ3/6,Density extrapolation
Author: Dapo Awolayo and Benjamin Tutolo
Author-email: benjamin.tutolo@ucalgary.ca
Maintainer: Dapo Awolayo
Maintainer-email: awolayoa@mcmaster.ca
Requires-Python: >=3.9,<4.0
Classifier: Intended Audience :: Science/Research
Classifier: Intended Audience :: Education
Classifier: Natural Language :: English
Classifier: Programming Language :: Python :: 3.7
Classifier: Programming Language :: Python :: 3.8
Classifier: Programming Language :: Python :: 3.9
Classifier: Programming Language :: Python :: 3.10
Classifier: Programming Language :: Python :: 3.11
Classifier: Programming Language :: Python :: 3.12
Classifier: Programming Language :: Python :: 3.13
Classifier: Topic :: Scientific/Engineering
Classifier: Topic :: Software Development :: Libraries :: Python Modules
Requires-Dist: importlib-metadata (>=4.4)
Requires-Dist: lxml (>=4.5.0)
Requires-Dist: matplotlib (>=3.2)
Requires-Dist: numpy (>=1.19.2)
Requires-Dist: pandas (>=1.5,<3.0)
Requires-Dist: scipy (>=1.2)
Project-URL: Documentation, https://pygcc.readthedocs.io/en/latest/index.html
Project-URL: Homepage, https://pygcc.readthedocs.io/en/
Project-URL: Repository, https://bitbucket.org/Tutolo-RTG/pygcc/src/master/
